README.rst
setup.py
tulipcore.py
tulipcore.egg-info/PKG-INFO
tulipcore.egg-info/SOURCES.txt
tulipcore.egg-info/dependency_links.txt
tulipcore.egg-info/requires.txt
tulipcore.egg-info/top_level.txt