Metadata-Version: 1.1
Name: tulipcore
Version: 0.1.0a2
Summary: An alternative Gevent core loop implementation with asyncio
Home-page: https://github.com/decentfox/tulipcore
Author: Fantix King
Author-email: fantix.king@gmail.com
License: UNKNOWN
Platform: UNKNOWN
Classifier: License :: OSI Approved :: MIT License
Classifier: Programming Language :: Python :: 3.3
Classifier: Programming Language :: Python :: 3.4
Classifier: Operating System :: MacOS :: MacOS X
Classifier: Operating System :: POSIX
Classifier: Topic :: Internet
Classifier: Topic :: Software Development :: Libraries :: Python Modules
Classifier: Intended Audience :: Developers
Classifier: Development Status :: 3 - Alpha
